{"sáng": 0, "tạnh": 1, "địa_điểm": 2, "cuối": 3, "mà_lại": 4, "quán": 5, "đói": 6, "sáng_mai": 7, "nay": 8, "lotte": 9, "học": 10, "ngày_kia": 11, "xin": 12, "chào": 13, "lát": 14, "hello": 15, "tối": 16, "tìm": 17, "đủ": 18, "hi": 19, "ăn": 20, "coffe": 21, "mưa": 22, "liệu": 23, "trưa": 24, "mỳ": 25, "lạnh": 26, "lắm": 27, "ngày_mai": 28, "vị_trí": 29, "chỗ": 30, "ngon": 31, "bánh": 32, "dậy": 33, "hôm_nay": 34, "thời_tiết": 35, "đẹp": 36, "tuần": 37, "nóng": 38, "mai": 39, "uống": 40, "chơi": 41, "ê": 42, "nghe": 43, "hà_nội": 44, "chiều": 45, "kfc": 46, "bot": 47, "trời": 48, "không": 49, "nhanh": 50, "phở": 51, "ngủ": 52, "bữa": 53, "gần": 54, "xong": 55, "quanh": 56, "dinh_dưỡng": 57, "rẻ": 58, "một_số": 59, "nhiệt_độ": 60, "nắng": 61, "bạn": 62}